LICENSE
MANIFEST.in
README
requirements.txt
setup.py
docs/Makefile
docs/api.rst
docs/conf.py
docs/index.rst
docs/setup.rst
docs/upgrade.rst
docs/_build/.keep
docs/_static/.keep
docs/_templates/.keep
ownpaste/__init__.py
ownpaste/__main__.py
ownpaste/auth.py
ownpaste/models.py
ownpaste/script.py
ownpaste/utils.py
ownpaste/version.py
ownpaste/views.py
ownpaste.egg-info/PKG-INFO
ownpaste.egg-info/SOURCES.txt
ownpaste.egg-info/dependency_links.txt
ownpaste.egg-info/entry_points.txt
ownpaste.egg-info/not-zip-safe
ownpaste.egg-info/requires.txt
ownpaste.egg-info/top_level.txt
ownpaste/migrations/README
ownpaste/migrations/__init__.py
ownpaste/migrations/manage.py
ownpaste/migrations/migrate.cfg
ownpaste/migrations/versions/001_Initial_schema.py
ownpaste/migrations/versions/002_Add_column_nonce_to_Ip.py
ownpaste/migrations/versions/__init__.py
ownpaste/static/styles.css
ownpaste/templates/base.html
ownpaste/templates/paste.html
ownpaste/templates/pastes.html