Metadata-Version: 1.1
Name: ownpaste
Version: 0.2.2
Summary: Private pastebin (server-side implementation)
Home-page: http://ownpaste.rtfd.org/
Author: Rafael G. Martins
Author-email: rafael@rafaelmartins.eng.br
License: BSD
Platform: UNKNOWN
Classifier: Development Status :: 3 - Alpha
Classifier: Environment :: Web Environment
Classifier: License :: OSI Approved :: BSD License
Classifier: Operating System :: OS Independent
Classifier: Topic :: Internet :: WWW/HTTP :: Dynamic Content
Classifier: Programming Language :: Python :: 2.7
